memory_mcp/__init__.py
memory_mcp/server.py
memory_mcp-0.1.0.dev1.dist-info/METADATA
memory_mcp-0.1.0.dev1.dist-info/WHEEL
memory_mcp-0.1.0.dev1.dist-info/top_level.txt
memory_mcp-0.1.0.dev1.dist-info/RECORD
