Metadata-Version: 2.1
Name: memory-mcp
Version: 0.1.0.dev1
Summary: A python implementation of AI memory in MCP
License: MIT
Project-URL: Repository, https://github.com/memodb-io/memory-mcp
Project-URL: Issues, https://github.com/memodb-io/memory-mcp/issues
Classifier: Development Status :: 4 - Beta
Classifier: Intended Audience :: Developers
Classifier: License :: OSI Approved :: MIT License
Classifier: Programming Language :: Python :: 3
Classifier: Programming Language :: Python :: 3.11
Classifier: Programming Language :: Python :: 3.12
Classifier: Programming Language :: Python :: 3.13
Requires-Python: >=3.11
Requires-Dist: mcp>=1.0.0
